<?xml version="1.0" encoding="UTF-8"?>
<!DOCTYPE suite SYSTEM "https://testng.org/testng-1.0.dtd">

<!--
    TestNG suite for Corporate Wellness data-driven tests.
    Reads test data from   : TestData/CorporateWellnessData.xlsx
    Writes status back into: same Excel (ActualStatus column)

    Coexists with the BDD/Cucumber framework:
      • Cucumber tests run via TestRunner.java (untouched)
      • TestNG tests run via this Testng.xml
      • Both use the same DriverFactory (ThreadLocal) — no conflict
-->
<suite name="CorporateWellnessSuite" verbose="2">

    <test name="CorporateWellnessRegistrationTests">
        <classes>
            <class name="org.example.CorporateWellnessTest">
                <methods>
                    <include name="testCorporateWellnessRegistration"/>
                </methods>
            </class>
        </classes>
    </test>

</suite>